README.md
setup.cfg
setup.py
distributions_AL/Binomialdistribution.py
distributions_AL/Gaussiandistribution.py
distributions_AL/Generaldistribution.py
distributions_AL/__init__.py
distributions_AL.egg-info/PKG-INFO
distributions_AL.egg-info/SOURCES.txt
distributions_AL.egg-info/dependency_links.txt
distributions_AL.egg-info/not-zip-safe
distributions_AL.egg-info/top_level.txt