Metadata-Version: 1.0
Name: distributions-AL
Version: 0.2
Summary: Gaussian distributions
Home-page: UNKNOWN
Author: Abhishek Lomsh
Author-email: abhisheklomsh@gmail.com
License: UNKNOWN
Platform: UNKNOWN
